simple_firebase_realtime_db/__init__.py
simple_firebase_realtime_db/firebase_realtime_db.py
simple_firebase_realtime_db/types/__init__.py
simple_firebase_realtime_db/types/json_data.py
simple_firebase_realtime_db-0.0.4.dist-info/LICENSE
simple_firebase_realtime_db-0.0.4.dist-info/METADATA
simple_firebase_realtime_db-0.0.4.dist-info/WHEEL
simple_firebase_realtime_db-0.0.4.dist-info/top_level.txt
simple_firebase_realtime_db-0.0.4.dist-info/RECORD
