Metadata-Version: 2.1
Name: simple-firebase-realtime-db
Version: 0.0.4
Summary: simple_firebase_realtime_db
Home-page: https://github.com/kkristof200/py_simple_firebase_realtime_db
Author: Kristóf-Attila Kovács
License: UNKNOWN
Platform: UNKNOWN
Classifier: Programming Language :: Python :: 3.4
Classifier: Programming Language :: Python :: 3.5
Classifier: Programming Language :: Python :: 3.6
Classifier: Programming Language :: Python :: 3.7
Classifier: Programming Language :: Python :: 3.8
Classifier: Programming Language :: Python :: 3.9
Classifier: License :: OSI Approved :: MIT License
Classifier: Operating System :: OS Independent
Requires-Python: >=3.4
Requires-Dist: firebase-admin (>=4.5.2)
Requires-Dist: jsoncodable (>=0.0.12)
Requires-Dist: noraise (>=0.0.10)
